mopidy_pandora/__init__.py
mopidy_pandora/backend.py
mopidy_pandora/client.py
mopidy_pandora/ext.conf
mopidy_pandora/frontend.py
mopidy_pandora/library.py
mopidy_pandora/listener.py
mopidy_pandora/playback.py
mopidy_pandora/uri.py
mopidy_pandora/utils.py
Mopidy_Pandora-1.1.1.dist-info/LICENSE
Mopidy_Pandora-1.1.1.dist-info/METADATA
Mopidy_Pandora-1.1.1.dist-info/WHEEL
Mopidy_Pandora-1.1.1.dist-info/entry_points.txt
Mopidy_Pandora-1.1.1.dist-info/top_level.txt
Mopidy_Pandora-1.1.1.dist-info/RECORD
